<?xml version = '1.0' encoding = 'UTF-8'?>
<Diagram class="oracle.dbtools.crest.swingui.relational.DPVRelational" name="Relational_1" id="F0F0694E-8C9F-C6AF-4446-65C8DF372DF1">
<createdBy>nathanbain</createdBy>
<createdTime>2015-04-21 23:51:39 UTC</createdTime>
<autoRoute>false</autoRoute>
<boxInbox>true</boxInbox>
<showLegend>false</showLegend>
<showLabels>false</showLabels>
<showRelAttributes>false</showRelAttributes>
<showGrid>false</showGrid>
<diagramColor>-1</diagramColor>
<display>false</display>
<notation>1</notation>
<objectViews>
<OView class="oracle.dbtools.crest.swingui.relational.TVTable" oid="2E13FA4A-7ADD-B134-D1F8-71E48BACF9AB" otype="Table" vid="BEF3163D-4E78-9321-A9A1-4B50D271D334">
<hideElementsInCurrentOnly>false</hideElementsInCurrentOnly>
<bounds x="325" y="506" width="269" height="174"/>
</OView>
<OView class="oracle.dbtools.crest.swingui.relational.TVTable" oid="47A7DCAF-2A39-18F5-7C7A-9692CA9AAA50" otype="Table" vid="FBF74D1E-77F2-D1FA-F2A1-A7B85E0D5BC3">
<hideElementsInCurrentOnly>false</hideElementsInCurrentOnly>
<bounds x="121" y="359" width="170" height="110"/>
</OView>
<OView class="oracle.dbtools.crest.swingui.relational.TVTable" oid="49D1B865-2E88-21D8-4E44-A96A4017316D" otype="Table" vid="C9B5685E-3E6B-88C3-326E-875B6547AFB0">
<hideElementsInCurrentOnly>false</hideElementsInCurrentOnly>
<bounds x="45" y="165" width="170" height="110"/>
</OView>
<OView class="oracle.dbtools.crest.swingui.relational.TVTable" oid="50709BF3-14EB-BCC5-776B-805FB17E09F0" otype="Table" vid="7747772A-6B59-AAC9-4452-911433A88B31">
<hideElementsInCurrentOnly>false</hideElementsInCurrentOnly>
<bounds x="395" y="341" width="170" height="110"/>
</OView>
<OView class="oracle.dbtools.crest.swingui.relational.TVTable" oid="96AE6A94-8190-8758-0489-847C767391F6" otype="Table" vid="9E8F3D46-381C-F395-DB05-5BFABBA10508">
<hideElementsInCurrentOnly>false</hideElementsInCurrentOnly>
<bounds x="345" y="130" width="214" height="144"/>
</OView>
<OView class="oracle.dbtools.crest.swingui.relational.TVTable" oid="DF7DBE6C-5A11-E441-BCFC-0DBAB4A73065" otype="Table" vid="6403FE2E-AADE-74C9-451C-645DD8A32355">
<hideElementsInCurrentOnly>false</hideElementsInCurrentOnly>
<bounds x="642" y="115" width="242" height="164"/>
</OView>
</objectViews>
<connectors>
<Connector class="oracle.dbtools.crest.swingui.relational.TVFKRelation" oid="0236494A-3B33-2B42-2D6D-5EDD128DB47B" otype="FKIndexAssociation" vid_source="BEF3163D-4E78-9321-A9A1-4B50D271D334" vid_target="FBF74D1E-77F2-D1FA-F2A1-A7B85E0D5BC3">
<hideElementsInCurrentOnly>false</hideElementsInCurrentOnly>
<lineWidth>1</lineWidth>
<points>
<point x="325" y="564"/>
<point x="257" y="564"/>
<point x="257" y="469"/>
</points>
</Connector>
<Connector class="oracle.dbtools.crest.swingui.relational.TVFKRelation" oid="4925CB9D-B4C5-B315-844B-EF0B00AFBF93" otype="FKIndexAssociation" vid_source="C9B5685E-3E6B-88C3-326E-875B6547AFB0" vid_target="9E8F3D46-381C-F395-DB05-5BFABBA10508">
<hideElementsInCurrentOnly>false</hideElementsInCurrentOnly>
<lineWidth>1</lineWidth>
<points>
<point x="215" y="209"/>
<point x="345" y="209"/>
</points>
</Connector>
<Connector class="oracle.dbtools.crest.swingui.relational.TVFKRelation" oid="7AA19FF3-A25B-F40D-FB60-53C4A51A6773" otype="FKIndexAssociation" vid_source="C9B5685E-3E6B-88C3-326E-875B6547AFB0" vid_target="FBF74D1E-77F2-D1FA-F2A1-A7B85E0D5BC3">
<hideElementsInCurrentOnly>false</hideElementsInCurrentOnly>
<lineWidth>1</lineWidth>
<points>
<point x="168" y="275"/>
<point x="168" y="359"/>
</points>
</Connector>
<Connector class="oracle.dbtools.crest.swingui.relational.TVFKRelation" oid="BACC1845-F4F8-2956-3D66-C3454CE0F6EA" otype="FKIndexAssociation" vid_source="9E8F3D46-381C-F395-DB05-5BFABBA10508" vid_target="7747772A-6B59-AAC9-4452-911433A88B31">
<hideElementsInCurrentOnly>false</hideElementsInCurrentOnly>
<lineWidth>1</lineWidth>
<points>
<point x="477" y="274"/>
<point x="477" y="341"/>
</points>
</Connector>
<Connector class="oracle.dbtools.crest.swingui.relational.TVFKRelation" oid="D364115E-C4F5-8190-153B-A021DD148E32" otype="FKIndexAssociation" vid_source="9E8F3D46-381C-F395-DB05-5BFABBA10508" vid_target="C9B5685E-3E6B-88C3-326E-875B6547AFB0">
<hideElementsInCurrentOnly>false</hideElementsInCurrentOnly>
<lineWidth>1</lineWidth>
<points>
<point x="345" y="209"/>
<point x="215" y="209"/>
</points>
</Connector>
<Connector class="oracle.dbtools.crest.swingui.relational.TVFKRelation" oid="E94A88E2-3780-3895-85DF-84FF6CB6B07A" otype="FKIndexAssociation" vid_source="9E8F3D46-381C-F395-DB05-5BFABBA10508" vid_target="6403FE2E-AADE-74C9-451C-645DD8A32355">
<hideElementsInCurrentOnly>false</hideElementsInCurrentOnly>
<lineWidth>1</lineWidth>
<points>
<point x="559" y="202"/>
<point x="642" y="202"/>
</points>
</Connector>
<Connector class="oracle.dbtools.crest.swingui.relational.TVFKRelation" oid="F2B848F2-02E1-26AB-07BA-A4251CC39EDB" otype="FKIndexAssociation" vid_source="BEF3163D-4E78-9321-A9A1-4B50D271D334" vid_target="7747772A-6B59-AAC9-4452-911433A88B31">
<hideElementsInCurrentOnly>false</hideElementsInCurrentOnly>
<lineWidth>1</lineWidth>
<points>
<point x="480" y="506"/>
<point x="480" y="451"/>
</points>
</Connector>
</connectors>
</Diagram>